[
  {
    "w": "引用文献",
    "p": "yǐnyòng wénxiàn",
    "m": "trích dẫn tài liệu, dẫn nguồn",
    "cat": "academic"
  },
  {
    "w": "样本容量",
    "p": "yàngběn róngliang",
    "m": "kích cỡ mẫu, cỡ mẫu nghiên cứu",
    "cat": "research"
  },
  {
    "w": "显著性",
    "p": "xiǎnzhùxìng",
    "m": "ý nghĩa thống kê, tính có ý nghĩa",
    "cat": "research"
  },
  {
    "w": "据此判断",
    "p": "jùcǐ pànduàn",
    "m": "từ đó mà phán đoán, căn cứ vào đây để đánh giá",
    "cat": "academic"
  },
  {
    "w": "从理论上讲",
    "p": "cóng lǐlùn shàng jiǎng",
    "m": "về mặt lý thuyết mà nói",
    "cat": "academic"
  },
  {
    "w": "就实践而言",
    "p": "jiù shíjiàn éryán",
    "m": "đối với thực tiễn mà nói, xét về mặt thực tiễn",
    "cat": "academic"
  },
  {
    "w": "概而言之",
    "p": "gài éryán zhī",
    "m": "nói chung lại, tóm gọn lại",
    "cat": "academic"
  },
  {
    "w": "举棋不定",
    "p": "jǔqí bùdìng",
    "m": "lưỡng lự không quyết, phân vân không biết nên làm gì",
    "cat": "idiom"
  },
  {
    "w": "国家治理",
    "p": "guójiā zhìlǐ",
    "m": "quản trị nhà nước, điều hành quốc gia",
    "cat": "policy"
  },
  {
    "w": "依法行政",
    "p": "yīfǎ xíngzhèng",
    "m": "hành chính theo pháp luật, quản lý nhà nước bằng pháp luật",
    "cat": "law"
  },
  {
    "w": "全面依法治国",
    "p": "quánmiàn yīfǎ zhìguó",
    "m": "toàn diện trị quốc theo pháp luật",
    "cat": "policy"
  },
  {
    "w": "行政执法",
    "p": "xíngzhèng zhífǎ",
    "m": "thực thi hành chính, chấp hành pháp luật",
    "cat": "law"
  },
  {
    "w": "云计算平台",
    "p": "yún jìsuàn píngtái",
    "m": "nền tảng điện toán đám mây",
    "cat": "tech"
  },
  {
    "w": "环境污染",
    "p": "huánjìng wūrǎn",
    "m": "ô nhiễm môi trường",
    "cat": "environment"
  },
  {
    "w": "伦理准则",
    "p": "lúnlǐ zhǔnzé",
    "m": "chuẩn mực đạo đức, tiêu chuẩn luân lý",
    "cat": "policy"
  },
  {
    "w": "机会均等",
    "p": "jīhuì jūnděng",
    "m": "cơ hội bình đẳng, bình đẳng về cơ hội",
    "cat": "society"
  },
  {
    "w": "文化创新",
    "p": "wénhuà chuàngxīn",
    "m": "đổi mới văn hóa, sáng tạo trong lĩnh vực văn hóa",
    "cat": "culture"
  },
  {
    "w": "审美观念",
    "p": "shěnměi guānniàn",
    "m": "quan niệm thẩm mỹ, quan điểm về cái đẹp",
    "cat": "culture"
  },
  {
    "w": "艺术鉴赏",
    "p": "yìshù jiànshǎng",
    "m": "thưởng thức nghệ thuật, thẩm định nghệ thuật",
    "cat": "culture"
  }
]